setup.py
x_utils.egg-info/PKG-INFO
x_utils.egg-info/SOURCES.txt
x_utils.egg-info/dependency_links.txt
x_utils.egg-info/top_level.txt
xutils/__init__.py
xutils/assert_utils.py
xutils/config_utils.py
xutils/custom_logger.py
xutils/decorators.py
xutils/misc.py
xutils/string_utils.py
xutils/test_runner.py
xutils/bar_builder/__init__.py
xutils/bar_builder/bar.py
xutils/bar_builder/bar_utils.py
xutils/bar_builder/live_feed.py
xutils/bar_builder/polling_thread.py
xutils/bar_builder/resamplebase.py
xutils/date_utils/__init__.py
xutils/date_utils/calendar.py
xutils/date_utils/convert.py
xutils/date_utils/date.py
xutils/date_utils/enums.py
xutils/date_utils/misc.py
xutils/date_utils/period.py
xutils/date_utils/schedule.py
xutils/examples/__init__.py
xutils/examples/clock.py
xutils/examples/date_utils.py
xutils/examples/exception_example.py
xutils/examples/logger.py
xutils/examples/socket_client.py
xutils/examples/task0.py
xutils/examples/task_runner_example.py
xutils/examples/test_runner_example.py
xutils/examples/tushare_live_feed.py
xutils/indicator/__init__.py
xutils/indicator/dt.py
xutils/job_runner/__init__.py
xutils/job_runner/job.py
xutils/job_runner/socket_job.py
xutils/job_runner/socket_server.py
xutils/job_runner/socket_utils.py
xutils/tests/__init__.py
xutils/tests/test_assert.py
xutils/tests/test_calendar.py
xutils/tests/test_config_utils.py
xutils/tests/test_date.py
xutils/tests/test_main.py
xutils/tests/test_misc.py
xutils/tests/test_period.py
xutils/tests/test_schedule.py
xutils/tests/test_string_utils.py