Metadata-Version: 1.0
Name: x-utils
Version: 0.5.7
Summary: utils for quantitative research
Home-page: https://github.com/iLampard/x-utils
Author: iLampard
Author-email: UNKNOWN
License: Apache-2.0
Platform: UNKNOWN
